LICENSE
README.md
setup.cfg
setup.py
pynrfjprog/API.py
pynrfjprog/APIError.py
pynrfjprog/Hex.py
pynrfjprog/HighLevel.py
pynrfjprog/JLink.py
pynrfjprog/LowLevel.py
pynrfjprog/MultiAPI.py
pynrfjprog/Parameters.py
pynrfjprog/RTTAsyncIO.py
pynrfjprog/__init__.py
pynrfjprog.egg-info/PKG-INFO
pynrfjprog.egg-info/SOURCES.txt
pynrfjprog.egg-info/dependency_links.txt
pynrfjprog.egg-info/requires.txt
pynrfjprog.egg-info/top_level.txt
pynrfjprog/docs/__init__.py
pynrfjprog/docs/highlevelnrfjprogdll.h
pynrfjprog/docs/nrfdfu.h
pynrfjprog/docs/nrfjprog_release_notes.txt
pynrfjprog/docs/nrfjprogdll.h
pynrfjprog/examples/__init__.py
pynrfjprog/examples/highlevel_memory_read_write.py
pynrfjprog/examples/highlevel_program_hex.py
pynrfjprog/examples/memory_read_write.py
pynrfjprog/examples/nrf9160_pca20035_modem_upgrade_over_serial.py
pynrfjprog/examples/program_hex.py
pynrfjprog/examples/python_help.py
pynrfjprog/examples/rtt_asyncio.py
pynrfjprog/examples/rtt_callback.py
pynrfjprog/examples/rtt_synchronous.py
pynrfjprog/examples/hex_files/__init__.py
pynrfjprog/examples/hex_files/nrf51_dk_blinky.hex
pynrfjprog/examples/hex_files/nrf51_dk_rtt.hex
pynrfjprog/examples/hex_files/nrf52840_dk_blinky.hex
pynrfjprog/examples/hex_files/nrf52_dk_blinky.hex
pynrfjprog/examples/hex_files/nrf52_dk_rtt.hex
pynrfjprog/examples/hex_files/nrf53_dk_blinky.hex
pynrfjprog/examples/hex_files/nrf53_dk_rtt.hex
pynrfjprog/examples/hex_files/nrf9160_pca20035_firmware_upgrade_app_0.1.0.hex
pynrfjprog/examples/hex_files/nrf91_dk_blinky.hex
pynrfjprog/examples/hex_files/nrf91_dk_rtt.hex
pynrfjprog/lib_arm64/__init__.py
pynrfjprog/lib_arm64/jlinkarm_nrf_worker_linux
pynrfjprog/lib_arm64/libhighlevelnrfjprog.so
pynrfjprog/lib_arm64/libnrfdfu.so
pynrfjprog/lib_arm64/libnrfjprogdll.so
pynrfjprog/lib_armhf/__init__.py
pynrfjprog/lib_armhf/jlinkarm_nrf_worker_linux
pynrfjprog/lib_armhf/libhighlevelnrfjprog.so
pynrfjprog/lib_armhf/libnrfdfu.so
pynrfjprog/lib_armhf/libnrfjprogdll.so
pynrfjprog/lib_x64/__init__.py
pynrfjprog/lib_x64/highlevelnrfjprog.dll
pynrfjprog/lib_x64/jlinkarm_nrf_worker.exe
pynrfjprog/lib_x64/jlinkarm_nrf_worker_linux
pynrfjprog/lib_x64/jlinkarm_nrf_worker_osx
