Metadata-Version: 2.1
Name: pynrfjprog
Version: 10.19.0
Summary: A simple Python interface for the nrfjprog functionality
Home-page: http://www.nordicsemi.com/
Author: Nordic Semiconductor ASA
Author-email: sagtools@nordicsemi.no
License: Nordic 5-clause License
Keywords: nrfjprog pynrfjprog highlevelpynrfjprog
Classifier: Development Status :: 5 - Production/Stable
Classifier: Intended Audience :: Developers
Classifier: Operating System :: MacOS
Classifier: Operating System :: Microsoft :: Windows
Classifier: Operating System :: POSIX :: Linux
Classifier: Topic :: Software Development :: Build Tools
Classifier: Topic :: Software Development :: Debuggers
Classifier: Topic :: Software Development :: Embedded Systems
Classifier: Programming Language :: Python :: 3.7
Classifier: Programming Language :: Python :: 3.8
Classifier: Programming Language :: Python :: 3.9
Classifier: Programming Language :: Python :: 3.10
Classifier: License :: Other/Proprietary License
Requires-Python: >=3.7
License-File: LICENSE
